etsy_searcher/__init__.py
etsy_searcher/searcher.py
etsy_searcher/models/Result.py
etsy_searcher/models/__init__.py
etsy_searcher/utils/__init__.py
etsy_searcher/utils/generate_listing_cards_request_body.py
etsy_searcher/utils/prepare_request_body.py
etsy_searcher-1.0.5.dist-info/LICENSE
etsy_searcher-1.0.5.dist-info/METADATA
etsy_searcher-1.0.5.dist-info/WHEEL
etsy_searcher-1.0.5.dist-info/top_level.txt
etsy_searcher-1.0.5.dist-info/RECORD
